jax_russell/__init__.py
jax_russell/base.py
jax_russell/bsm.py
jax_russell/cli.py
jax_russell/jax_russell.py
jax_russell/trees.py
jax_russell-0.2.0.dist-info/LICENSE
jax_russell-0.2.0.dist-info/METADATA
jax_russell-0.2.0.dist-info/WHEEL
jax_russell-0.2.0.dist-info/entry_points.txt
jax_russell-0.2.0.dist-info/RECORD
