Metadata-Version: 2.1
Name: jax-russell
Version: 0.2.0
Summary: Financial options valuations and auto-diffed risk measures ("greeks" in Jax.
Home-page: https://github.com/SeanEaster/jax_russell
License: GPL-3.0-only
Author: Sean Easter
Author-email: sean@easter.ai
Requires-Python: >=3.11,<4.0
Classifier: Development Status :: 2 - Pre-Alpha
Classifier: Intended Audience :: Developers
Classifier: License :: OSI Approved :: GNU General Public License v3 (GPLv3)
Classifier: Natural Language :: English
Classifier: Programming Language :: Python :: 3
Classifier: Programming Language :: Python :: 3.11
Provides-Extra: dev
Provides-Extra: doc
Provides-Extra: test
Requires-Dist: black (>=23.7.0,<24.0.0) ; extra == "test"
Requires-Dist: bump2version (>=1.0.1,<2.0.0) ; extra == "dev"
Requires-Dist: click (==8.0.1)
Requires-Dist: flake8 (>=3.9.2,<4.0.0) ; extra == "test"
Requires-Dist: flake8-docstrings (>=1.6.0,<2.0.0) ; extra == "test"
Requires-Dist: isort (>=5.8.0,<6.0.0) ; extra == "test"
Requires-Dist: jax (>=0.4.14,<1)
Requires-Dist: jaxlib (>=0.4.14,<1)
Requires-Dist: jaxopt (>=0.8,<0.9)
Requires-Dist: jaxtyping (>=0.2.1,<1)
Requires-Dist: jinja2 (==3.0.3)
Requires-Dist: mkdocs (>=1.3.0,<2.0.0) ; extra == "doc"
Requires-Dist: mkdocs-autorefs (>=0.5.0,<0.6.0) ; extra == "doc"
Requires-Dist: mkdocs-include-markdown-plugin (>=1.0.0,<2.0.0) ; extra == "doc"
Requires-Dist: mkdocs-material (>=6.1.7,<7.0.0) ; extra == "doc"
Requires-Dist: mkdocs-material-extensions (>=1.0.1,<2.0.0)
Requires-Dist: mkdocstrings[python] (>=0.22.0,<0.23.0) ; extra == "doc"
Requires-Dist: mypy (>=0.982,<0.983) ; extra == "test"
Requires-Dist: pip (>=20.3.1,<21.0.0) ; extra == "dev"
Requires-Dist: pre-commit (>=2.12.0,<3.0.0) ; extra == "dev"
Requires-Dist: pymdown-extensions (>=9.4,<10.0)
Requires-Dist: pytest (>=7.4.0,<8.0.0) ; extra == "test"
Requires-Dist: pytest-cov (>=4.1.0,<5.0.0) ; extra == "test"
Requires-Dist: toml (>=0.10.2,<0.11.0) ; extra == "dev"
Requires-Dist: tox (>=4.10.0,<5.0.0) ; extra == "dev"
Requires-Dist: twine (>=3.3.0,<4.0.0) ; extra == "dev"
Requires-Dist: typeguard (>=4.1.2,<4.1.4)
Requires-Dist: virtualenv (>=20.2.2,<21.0.0) ; extra == "dev"
